diamond/__init__.py
diamond/c.py
diamond_c-0.0.2.dist-info/LICENSE
diamond_c-0.0.2.dist-info/METADATA
diamond_c-0.0.2.dist-info/WHEEL
diamond_c-0.0.2.dist-info/top_level.txt
diamond_c-0.0.2.dist-info/RECORD
