Metadata-Version: 2.1
Name: diamond-c
Version: 0.0.2
Summary: A small package to test diamond dependencies
Home-page: https://github.com/thibaultduponchelle/diamond-c
Author: Thibault Duponchelle
Author-email: thibault.duponchelle@gmail.com
License: UNKNOWN
Project-URL: Bug Tracker, https://github.com/thibaultduponchelle/diamond-c/issues
Platform: UNKNOWN
Classifier: Programming Language :: Python :: 3
Classifier: License :: OSI Approved :: MIT License
Classifier: Operating System :: OS Independent
Requires-Python: >=3.6
License-File: LICENSE
Requires-Dist: diamond-d (>=0)
Requires-Dist: diamond-e (==0.0.2)
